kg_traefik2/__init__.py
kg_traefik2/builder.py
kg_traefik2/configfile.py
kg_traefik2/option.py
kg_traefik2/py.typed
kg_traefik2/tests/__init__.py
kg_traefik2/tests/test_builder.py
tests/__init__.py
tests/test_builder.py
kg_traefik2-0.8.0.dist-info/LICENSE
kg_traefik2-0.8.0.dist-info/METADATA
kg_traefik2-0.8.0.dist-info/WHEEL
kg_traefik2-0.8.0.dist-info/top_level.txt
kg_traefik2-0.8.0.dist-info/RECORD
