Metadata-Version: 2.1
Name: kg-traefik2
Version: 0.8.0
Summary: KubraGen Builder: Traefik 2
Home-page: https://github.com/RangelReale/kg_traefik2
Author: Rangel Reale
Author-email: rangelreale@gmail.com
License: UNKNOWN
Platform: UNKNOWN
Classifier: Programming Language :: Python :: 3
Classifier: License :: OSI Approved :: MIT License
Classifier: Operating System :: OS Independent
Requires-Python: >=3.6
Requires-Dist: kubragen (>=0.8.2)
Requires-Dist: kgp-configrendertoml (>=0.8.0)
